odoo9_addon_document_page_quality_manual-9.0.1.0.0.99.dev3-py2.7-nspkg.pth
odoo9_addon_document_page_quality_manual-9.0.1.0.0.99.dev3.dist-info/DESCRIPTION.rst
odoo9_addon_document_page_quality_manual-9.0.1.0.0.99.dev3.dist-info/METADATA
odoo9_addon_document_page_quality_manual-9.0.1.0.0.99.dev3.dist-info/RECORD
odoo9_addon_document_page_quality_manual-9.0.1.0.0.99.dev3.dist-info/WHEEL
odoo9_addon_document_page_quality_manual-9.0.1.0.0.99.dev3.dist-info/metadata.json
odoo9_addon_document_page_quality_manual-9.0.1.0.0.99.dev3.dist-info/namespace_packages.txt
odoo9_addon_document_page_quality_manual-9.0.1.0.0.99.dev3.dist-info/top_level.txt
odoo_addons/document_page_quality_manual/README.rst
odoo_addons/document_page_quality_manual/__init__.py
odoo_addons/document_page_quality_manual/__openerp__.py
odoo_addons/document_page_quality_manual/data/document_page.xml
odoo_addons/document_page_quality_manual/i18n/ar.po
odoo_addons/document_page_quality_manual/i18n/bg.po
odoo_addons/document_page_quality_manual/i18n/ca.po
odoo_addons/document_page_quality_manual/i18n/cs.po
odoo_addons/document_page_quality_manual/i18n/da.po
odoo_addons/document_page_quality_manual/i18n/de.po
odoo_addons/document_page_quality_manual/i18n/document_page_quality_manual.pot
odoo_addons/document_page_quality_manual/i18n/es.po
odoo_addons/document_page_quality_manual/i18n/es_CR.po
odoo_addons/document_page_quality_manual/i18n/es_MX.po
odoo_addons/document_page_quality_manual/i18n/es_VE.po
odoo_addons/document_page_quality_manual/i18n/fi.po
odoo_addons/document_page_quality_manual/i18n/fr.po
odoo_addons/document_page_quality_manual/i18n/gl.po
odoo_addons/document_page_quality_manual/i18n/hr.po
odoo_addons/document_page_quality_manual/i18n/hu.po
odoo_addons/document_page_quality_manual/i18n/it.po
odoo_addons/document_page_quality_manual/i18n/ja.po
odoo_addons/document_page_quality_manual/i18n/lv.po
odoo_addons/document_page_quality_manual/i18n/mn.po
odoo_addons/document_page_quality_manual/i18n/nb.po
odoo_addons/document_page_quality_manual/i18n/nl.po
odoo_addons/document_page_quality_manual/i18n/oc.po
odoo_addons/document_page_quality_manual/i18n/pt.po
odoo_addons/document_page_quality_manual/i18n/pt_BR.po
odoo_addons/document_page_quality_manual/i18n/ro.po
odoo_addons/document_page_quality_manual/i18n/ru.po
odoo_addons/document_page_quality_manual/i18n/sk.po
odoo_addons/document_page_quality_manual/i18n/sl.po
odoo_addons/document_page_quality_manual/i18n/sr@latin.po
odoo_addons/document_page_quality_manual/i18n/sv.po
